
{"Martino Conversano": [{"sensortype": "heart_rate", "ID_sensor": "sensor_heart_rate", "patient": "Martino Conversano", "measure": "bpm", "communication": {"basetopic": "molinette/patients/martino_conversano", "complete_topic": "molinette/patients/martino_conversano/heart_rate/sensor_heart_rate", "broker": "test.mosquitto.org", "port": 1883}, "insert-timestamp": 1676802137.172649}, {"sensortype": "body_temperature", "ID_sensor": "body_temperature", "patient": "Martino Conversano", "measure": "Celsius degrees", "communication": {"basetopic": "molinette/patients/martino_conversano", "complete_topic": "molinette/patients/martino_conversano/body_temperature/body_temperature", "broker": "test.mosquitto.org", "port": 1883}, "insert-timestamp": 1676802152.9519699}], "Simona Chiurato": [{"sensortype": "heart_rate", "ID_sensor": "sensor_heart_rate", "patient": "Simona Chiurato", "measure": "bpm", "communication": {"basetopic": "molinette/patients/simona_chiurato", "complete_topic": "molinette/patients/simona_chiurato/heart_rate/sensor_heart_rate", "broker": "test.mosquitto.org", "port": 1883}, "insert-timestamp": 1676802142.9360244}]}

